standingssync/__init__.py
standingssync/admin.py
standingssync/app_settings.py
standingssync/apps.py
standingssync/auth_hooks.py
standingssync/helpers.py
standingssync/managers.py
standingssync/models.py
standingssync/providers.py
standingssync/tasks.py
standingssync/urls.py
standingssync/views.py
standingssync/core/__init__.py
standingssync/core/esi_api.py
standingssync/core/esi_contacts.py
standingssync/management/commands/standingssync_calc_war_ids.py
standingssync/migrations/0001_initial_new_2.py
standingssync/migrations/0002_improve_sync_logic.py
standingssync/migrations/__init__.py
standingssync/static/standingssync/base.css
standingssync/templates/admin/standingssync/evewar/change_list.html
standingssync/templates/standingssync/_base.html
standingssync/templates/standingssync/characters.html
standingssync/templates/standingssync/wars.html
standingssync/templates/standingssync/partial/menu.html
standingssync/templates/standingssync/partial/war_participant.html
standingssync/templatetags/__init__.py
standingssync/templatetags/standingssync.py
standingssync/tests/__init__.py
standingssync/tests/factories.py
standingssync/tests/test_admin.py
standingssync/tests/test_integration.py
standingssync/tests/test_managers.py
standingssync/tests/test_models.py
standingssync/tests/test_tasks.py
standingssync/tests/test_templatetags.py
standingssync/tests/test_views.py
standingssync/tests/utils.py
standingssync/tests/core/__init__.py
standingssync/tests/core/test_esi_api.py
standingssync/tests/core/test_esi_contacts.py
aa_standingssync-1.10.0.dist-info/LICENSE
aa_standingssync-1.10.0.dist-info/WHEEL
aa_standingssync-1.10.0.dist-info/METADATA
aa_standingssync-1.10.0.dist-info/RECORD
